marso/__init__.py
marso/_compatibility.py
marso/cache.py
marso/file_io.py
marso/grammar.py
marso/normalizer.py
marso/parser.py
marso/tree.py
marso/utils.py
marso/__pycache__/__init__.cpython-37.pyc
marso/__pycache__/_compatibility.cpython-37.pyc
marso/__pycache__/cache.cpython-37.pyc
marso/__pycache__/demo_grammar.cpython-37.pyc
marso/__pycache__/file_io.cpython-37.pyc
marso/__pycache__/grammar.cpython-37.pyc
marso/__pycache__/normalizer.cpython-37.pyc
marso/__pycache__/parser.cpython-37.pyc
marso/__pycache__/tree.cpython-37.pyc
marso/__pycache__/utils.cpython-37.pyc
marso/demo/demo_grammar.py
marso/demo/__pycache__/demo_grammar.cpython-37.pyc
marso/grammar/demo.txt
marso/grammar/python36.txt
marso/grammar/python37.txt
marso/grammar/python38.txt
marso/grammar/python39.txt
marso/pgen2/__init__.py
marso/pgen2/generator.py
marso/pgen2/grammar_parser.py
marso/pgen2/__pycache__/__init__.cpython-37.pyc
marso/pgen2/__pycache__/generator.cpython-37.pyc
marso/pgen2/__pycache__/grammar_parser.cpython-37.pyc
marso/python/__init__.py
marso/python/diff.py
marso/python/errors.py
marso/python/parser.py
marso/python/pep8.py
marso/python/prefix.py
marso/python/token.py
marso/python/tokenizer.py
marso/python/tree.py
marso/python/__pycache__/__init__.cpython-37.pyc
marso/python/__pycache__/diff.cpython-37.pyc
marso/python/__pycache__/errors.cpython-37.pyc
marso/python/__pycache__/parser.cpython-37.pyc
marso/python/__pycache__/pep8.cpython-37.pyc
marso/python/__pycache__/prefix.cpython-37.pyc
marso/python/__pycache__/token.cpython-37.pyc
marso/python/__pycache__/tokenize.cpython-37.pyc
marso/python/__pycache__/tokenizer.cpython-37.pyc
marso/python/__pycache__/tree.cpython-37.pyc
marso-0.0.3.dist-info/AUTHORS.txt
marso-0.0.3.dist-info/LICENSE.txt
marso-0.0.3.dist-info/METADATA
marso-0.0.3.dist-info/WHEEL
marso-0.0.3.dist-info/top_level.txt
marso-0.0.3.dist-info/RECORD
