Metadata-Version: 2.1
Name: marso
Version: 0.0.3
Summary: A Move Parser
Home-page: https://github.com/yuan-xy/marso
Author: Yuan xy
Author-email: yuan_xin_yu@hotmail.com
Maintainer: Yuan xy
Maintainer-email: yuan_xin_yu@hotmail.com
License: MIT
Keywords: move/libra parser
Platform: any
Classifier: Development Status :: 4 - Beta
Classifier: Environment :: Plugins
Classifier: Intended Audience :: Developers
Classifier: License :: OSI Approved :: MIT License
Classifier: Operating System :: OS Independent
Classifier: Programming Language :: Python :: 3
Classifier: Topic :: Software Development :: Libraries :: Python Modules
Classifier: Topic :: Text Editors :: Integrated Development Environments (IDE)
Classifier: Topic :: Utilities
Requires-Python: >=3.7
Provides-Extra: testing
Requires-Dist: docopt ; extra == 'testing'
Requires-Dist: pytest (>=3.0.7) ; extra == 'testing'
